stac_generator/LICENSE
stac_generator/__init__.py
stac_generator/core/__init__.py
stac_generator/core/baker.py
stac_generator/core/bulk_output.py
stac_generator/core/exceptions.py
stac_generator/core/generator.py
stac_generator/core/handler_picker.py
stac_generator/core/input.py
stac_generator/core/mapping.py
stac_generator/core/output.py
stac_generator/core/process_config.py
stac_generator/core/utils.py
stac_generator/plugins/__init__.py
stac_generator/plugins/bulk_outputs/__init__.py
stac_generator/plugins/bulk_outputs/elasticsearch.py
stac_generator/plugins/bulk_outputs/rabbit_mq.py
stac_generator/plugins/bulk_outputs/standard_out.py
stac_generator/plugins/inputs/__init__.py
stac_generator/plugins/inputs/elasticsearch_aggregation.py
stac_generator/plugins/inputs/file_system.py
stac_generator/plugins/inputs/intake_esm.py
stac_generator/plugins/inputs/object_store.py
stac_generator/plugins/inputs/rabbit_mq.py
stac_generator/plugins/inputs/solr.py
stac_generator/plugins/inputs/text_file.py
stac_generator/plugins/inputs/thredds.py
stac_generator/plugins/mappings/__init__.py
stac_generator/plugins/mappings/jinja2.py
stac_generator/plugins/mappings/stac.py
stac_generator/plugins/outputs/__init__.py
stac_generator/plugins/outputs/elasticsearch.py
stac_generator/plugins/outputs/intake_esm.py
stac_generator/plugins/outputs/json_file.py
stac_generator/plugins/outputs/rabbit_mq.py
stac_generator/plugins/outputs/stac_fastapi.py
stac_generator/plugins/outputs/standard_out.py
stac_generator/plugins/outputs/text_file.py
stac_generator/scripts/__init__.py
stac_generator/scripts/recipe_keys.py
stac_generator/scripts/stac_generator.py
stac_generator-2.0.1.dist-info/LICENSE.txt
stac_generator-2.0.1.dist-info/METADATA
stac_generator-2.0.1.dist-info/WHEEL
stac_generator-2.0.1.dist-info/entry_points.txt
stac_generator-2.0.1.dist-info/RECORD
